gsplat/__init__.py
gsplat/_helper.py
gsplat/distributed.py
gsplat/exporter.py
gsplat/profile.py
gsplat/relocation.py
gsplat/rendering.py
gsplat/utils.py
gsplat/version.py
gsplat/compression/__init__.py
gsplat/compression/png_compression.py
gsplat/compression/sort.py
gsplat/cuda/__init__.py
gsplat/cuda/_backend.py
gsplat/cuda/_torch_impl.py
gsplat/cuda/_torch_impl_2dgs.py
gsplat/cuda/_wrapper.py
gsplat/cuda/ext.cpp
gsplat/cuda/csrc/Adam.cpp
gsplat/cuda/csrc/Adam.h
gsplat/cuda/csrc/AdamCUDA.cu
gsplat/cuda/csrc/Intersect.cpp
gsplat/cuda/csrc/Intersect.h
gsplat/cuda/csrc/IntersectTile.cu
gsplat/cuda/csrc/Null.cpp
gsplat/cuda/csrc/Null.h
gsplat/cuda/csrc/NullCUDA.cu
gsplat/cuda/csrc/Projection.cpp
gsplat/cuda/csrc/Projection.h
gsplat/cuda/csrc/Projection2DGS.cuh
gsplat/cuda/csrc/Projection2DGSFused.cu
gsplat/cuda/csrc/Projection2DGSPacked.cu
gsplat/cuda/csrc/ProjectionEWA3DGSFused.cu
gsplat/cuda/csrc/ProjectionEWA3DGSPacked.cu
gsplat/cuda/csrc/ProjectionEWASimple.cu
gsplat/cuda/csrc/ProjectionUT3DGSFused.cu
gsplat/cuda/csrc/QuatScaleToCovar.cpp
gsplat/cuda/csrc/QuatScaleToCovar.h
gsplat/cuda/csrc/QuatScaleToCovarCUDA.cu
gsplat/cuda/csrc/Rasterization.cpp
gsplat/cuda/csrc/Rasterization.h
gsplat/cuda/csrc/RasterizeToIndices2DGS.cu
gsplat/cuda/csrc/RasterizeToIndices3DGS.cu
gsplat/cuda/csrc/RasterizeToPixels2DGSBwd.cu
gsplat/cuda/csrc/RasterizeToPixels2DGSFwd.cu
gsplat/cuda/csrc/RasterizeToPixels3DGSBwd.cu
gsplat/cuda/csrc/RasterizeToPixels3DGSFwd.cu
gsplat/cuda/csrc/RasterizeToPixelsFromWorld3DGSBwd.cu
gsplat/cuda/csrc/RasterizeToPixelsFromWorld3DGSFwd.cu
gsplat/cuda/csrc/Relocation.cpp
gsplat/cuda/csrc/Relocation.h
gsplat/cuda/csrc/RelocationCUDA.cu
gsplat/cuda/csrc/SphericalHarmonics.cpp
gsplat/cuda/csrc/SphericalHarmonics.h
gsplat/cuda/csrc/SphericalHarmonicsCUDA.cu
gsplat/cuda/include/Cameras.cuh
gsplat/cuda/include/Cameras.h
gsplat/cuda/include/Common.h
gsplat/cuda/include/Ops.h
gsplat/cuda/include/Utils.cuh
gsplat/optimizers/__init__.py
gsplat-1.5.2.dist-info/licenses/LICENSE
gsplat-1.5.2.dist-info/METADATA
gsplat-1.5.2.dist-info/WHEEL
gsplat-1.5.2.dist-info/top_level.txt
gsplat-1.5.2.dist-info/RECORD
